xdfem/XPyFEM.py
xdfem/__init__.py
xdfem/common.py
xdfem/decorators.py
xdfem/gmsh2dat.py
xdfem/gmshhandler.py
xdfem/meshiohandler.py
xdfem/meshstruct.py
xdfem/ofemhandler.py
xdfem/pyfemhandler.py
xdfem/pyfemrun.py
xdfem/xfemmesh.py
xdfem/adapters/__init__.py
xdfem/adapters/msh.py
xdfem/adapters/sap2000.py
xdfem/ofem/__init__.py
xdfem/ofem/libofemc.dylib
xdfem/ofem/libofemc.py
xdfem-2024.8.1.dist-info/METADATA
xdfem-2024.8.1.dist-info/WHEEL
xdfem-2024.8.1.dist-info/top_level.txt
xdfem-2024.8.1.dist-info/RECORD
